datastory/__init__.py
datastory/config/__init__.py
datastory/core/__init__.py
datastory/core/analyzer.py
datastory/core/insights.py
datastory/formatters/__init__.py
datastory/formatters/report_formatter.py
datastory/loaders/__init__.py
datastory/loaders/data_loader.py
datastory/narration/__init__.py
datastory/narration/generator.py
datastory/utils/__init__.py
datastory/utils/helpers.py
datastory_ai-0.1.0.dist-info/licenses/LICENSE
datastory_ai-0.1.0.dist-info/METADATA
datastory_ai-0.1.0.dist-info/WHEEL
datastory_ai-0.1.0.dist-info/entry_points.txt
datastory_ai-0.1.0.dist-info/top_level.txt
datastory_ai-0.1.0.dist-info/RECORD
