Metadata-Version: 2.4
Name: datastory-ai
Version: 0.1.0
Summary: Automatic Storytelling from Data - Turn raw data into compelling business narratives
Home-page: https://github.com/idrissbado/DataStory
Author: Idriss Bado
Author-email: Idriss Bado <your.email@example.com>
Maintainer-email: Idriss Bado <your.email@example.com>
License: MIT
Project-URL: Homepage, https://github.com/idrissbado/DataStory
Project-URL: Documentation, https://github.com/idrissbado/DataStory#readme
Project-URL: Repository, https://github.com/idrissbado/DataStory
Project-URL: Issues, https://github.com/idrissbado/DataStory/issues
Keywords: data analysis,business intelligence,narrative,storytelling,automated reports,data science
Classifier: Development Status :: 4 - Beta
Classifier: Intended Audience :: Developers
Classifier: Intended Audience :: Science/Research
Classifier: Intended Audience :: Financial and Insurance Industry
Classifier: Topic :: Scientific/Engineering :: Information Analysis
Classifier: Topic :: Office/Business
Classifier: License :: OSI Approved :: MIT License
Classifier: Programming Language :: Python :: 3
Classifier: Programming Language :: Python :: 3.8
Classifier: Programming Language :: Python :: 3.9
Classifier: Programming Language :: Python :: 3.10
Classifier: Programming Language :: Python :: 3.11
Classifier: Programming Language :: Python :: 3.12
Requires-Python: >=3.8
License-File: LICENSE
Requires-Dist: pandas>=1.3.0
Requires-Dist: numpy>=1.21.0
Provides-Extra: full
Requires-Dist: matplotlib>=3.4.0; extra == "full"
Requires-Dist: openpyxl>=3.0.0; extra == "full"
Requires-Dist: reportlab>=3.6.0; extra == "full"
Provides-Extra: dev
Requires-Dist: pytest>=7.0.0; extra == "dev"
Requires-Dist: black>=22.0.0; extra == "dev"
Requires-Dist: flake8>=4.0.0; extra == "dev"
Dynamic: author
Dynamic: home-page
Dynamic: license-file
Dynamic: requires-python
